LICENSE
README.md
setup.cfg
setup.py
kfp_server_api/__init__.py
kfp_server_api/api_client.py
kfp_server_api/configuration.py
kfp_server_api/exceptions.py
kfp_server_api/rest.py
kfp_server_api.egg-info/PKG-INFO
kfp_server_api.egg-info/SOURCES.txt
kfp_server_api.egg-info/dependency_links.txt
kfp_server_api.egg-info/requires.txt
kfp_server_api.egg-info/top_level.txt
kfp_server_api/api/__init__.py
kfp_server_api/api/auth_service_api.py
kfp_server_api/api/experiment_service_api.py
kfp_server_api/api/healthz_service_api.py
kfp_server_api/api/pipeline_service_api.py
kfp_server_api/api/pipeline_upload_service_api.py
kfp_server_api/api/recurring_run_service_api.py
kfp_server_api/api/report_service_api.py
kfp_server_api/api/run_service_api.py
kfp_server_api/api/visualization_service_api.py
kfp_server_api/models/__init__.py
kfp_server_api/models/authorize_request_resources.py
kfp_server_api/models/authorize_request_verb.py
kfp_server_api/models/googlerpc_status.py
kfp_server_api/models/pipeline_task_detail_child_task.py
kfp_server_api/models/predicate_int_values.py
kfp_server_api/models/predicate_long_values.py
kfp_server_api/models/predicate_string_values.py
kfp_server_api/models/protobuf_any.py
kfp_server_api/models/protobuf_null_value.py
kfp_server_api/models/recurring_run_mode.py
kfp_server_api/models/v2beta1_artifact_list.py
kfp_server_api/models/v2beta1_create_pipeline_and_version_request.py
kfp_server_api/models/v2beta1_cron_schedule.py
kfp_server_api/models/v2beta1_experiment.py
kfp_server_api/models/v2beta1_experiment_storage_state.py
kfp_server_api/models/v2beta1_filter.py
kfp_server_api/models/v2beta1_get_healthz_response.py
kfp_server_api/models/v2beta1_list_experiments_response.py
kfp_server_api/models/v2beta1_list_pipeline_versions_response.py
kfp_server_api/models/v2beta1_list_pipelines_response.py
kfp_server_api/models/v2beta1_list_recurring_runs_response.py
kfp_server_api/models/v2beta1_list_runs_response.py
kfp_server_api/models/v2beta1_periodic_schedule.py
kfp_server_api/models/v2beta1_pipeline.py
kfp_server_api/models/v2beta1_pipeline_task_detail.py
kfp_server_api/models/v2beta1_pipeline_task_executor_detail.py
