Metadata-Version: 2.4
Name: kfp-server-api
Version: 2.15.2
Summary: Kubeflow Pipelines API
Home-page: https://github.com/kubeflow/pipelines
Author: google
Author-email: kubeflow-pipelines@google.com
License: Apache 2.0
Keywords: OpenAPI,OpenAPI-Generator,Kubeflow Pipelines API
License-File: LICENSE
Requires-Dist: urllib3>=1.15
Requires-Dist: six>=1.10
Requires-Dist: certifi
Requires-Dist: python-dateutil
Dynamic: author
Dynamic: author-email
Dynamic: description
Dynamic: home-page
Dynamic: keywords
Dynamic: license
Dynamic: license-file
Dynamic: requires-dist
Dynamic: summary
